TDM/tdm_deserializer.v
module tdm_deserializer (
	clock,
	reset,
	tdm_data,
	tdm_sync,
	tdm_clk,
	word_ready,
	ch0,
	ch1,
	ch2,
	ch3,
	ch4	
);

//----- Parameters   -----
parameter SIZE_32T = 32	;
parameter SIZE_08T = 8	;
parameter CH0_DEC = 4'h0;
parameter CH1_DEC = 4'h1;
parameter CH2_DEC = 4'h2;
parameter CH3_DEC = 4'h3;
parameter CH4_DEC = 4'h4;
parameter IDLE	  = 4'hF;

//----- Input Ports  -----
input clock	;
input reset	;
input tdm_data	;
input tdm_sync	;
input tdm_clk	;

//----- Output Ports -----
output word_ready	 ;
output [SIZE_32T-1:0] ch0;
output [SIZE_32T-1:0] ch1;
output [SIZE_32T-1:0] ch2;
output [SIZE_32T-1:0] ch3;
output [SIZE_32T-1:0] ch4;

//----- Registers    -----
reg			ready	;
reg [SIZE_08T-1:0]	count 	;
reg [SIZE_32T-1:0]	ch0_data;
reg [SIZE_32T-1:0]	ch1_data;
reg [SIZE_32T-1:0]	ch2_data;
reg [SIZE_32T-1:0]	ch3_data;
reg [SIZE_32T-1:0]	ch4_data;

assign word_ready = ready;
assign ch0 = ch0_data;
assign ch1 = ch1_data;
assign ch2 = ch2_data;
assign ch3 = ch3_data;
assign ch4 = ch4_data;

always @ (posedge tdm_clk or posedge reset)	
begin
	if (reset) begin
		count 	 = 8'hFF;
		ch0_data = 8'h00;
		ch1_data = 8'h00;
		ch2_data = 8'h00;
		ch3_data = 8'h00;
		ch4_data = 8'h00;
		ready	 = 1'b0;
	end else begin
		case(count[7:4]) 
			IDLE:   begin				
					if (tdm_sync == 1'b1) begin
						count <= 8'h00;
					end
					if (ready == 1'b1) begin
						ready <= 1'b0;
					end
				end
			CH0_DEC:begin
					ch0_data <= {ch0_data[30:0], tdm_data};
					count 	 <= (count + 1'b1);
				end 
			CH1_DEC:begin
					ch1_data <= {ch1_data[30:0], tdm_data};
					count 	 <= count + 1;
				end 
			CH2_DEC:begin
					ch2_data <= {ch2_data[30:0], tdm_data};
					count 	 <= count + 1;
				end 
			CH3_DEC:begin
					ch3_data <= {ch3_data[30:0], tdm_data};
					count 	 <= count + 1;
				end 
			CH4_DEC:begin
					ch4_data <= {ch4_data[30:0], tdm_data};
					if (count == 8'h4F) begin
						count <= 8'hFF;
						ready <= 1'b1;
					end else begin
						count <= count + 1;
					end
				end 
		endcase
	end
end

endmodule

TDM/test.v
`timescale 1ns/10ps

//`include "tdm_deserializer.v"

module test_tdm_deserializer;

	reg [159:0] mem = { 32'h555555FA, 32'h555555FB, 32'h555555FC, 32'h555555FE,32'h555555FF};
	reg reset, fsync, data, clock;

	wire ready;
	wire [31:0] channel0;
	wire [31:0] channel1;
	wire [31:0] channel2;
	wire [31:0] channel3;
	wire [31:0] channel4;

	integer i, j;

	initial begin
		for (i=0; i < 5; i = i + 1) begin
			for (j=1; j < 6; j = j + 1) begin
				mem[j-1] = { 28'h555555A, $realtobits(j) };
			end
		end		
		$monitor ("Starting testbench...");
		$dumpfile("rawwaves_testrun.vcd");
		$dumpvars(0);
		
		clock = 0;
		reset = 0;
		fsync = 0;
		#5  reset = 1;
		#10 reset = 0;
		fsync = 1; 
		#1  fsync = 0;
		for (i=0; i < 160; i = i + 1) begin
			#2 data = mem[i];
		end
		$finish;
	end

	always begin
		#1 clock = !clock;
	end

	tdm_deserializer deserializer(
		.clock	   (clock),
		.reset	   (reset),
		.tdm_data  (data),
		.tdm_sync  (fsync),
		.tdm_clk   (clock),
		.word_ready(ready),
		.ch0	   (channel0),
		.ch1	   (channel1),
		.ch2	   (channel2),
		.ch3	   (channel3),
		.ch4	   (channel4)	
	);

endmodule

TDM/rawwaves_testrun.vcd
$date
	Tue Nov 07 00:03:08 2023
$end
$version
	Icarus Verilog
$end
$timescale
	10ps
$end
$scope module test_tdm_deserializer $end
$var wire 1 ! ready $end
$var wire 32 " channel4 [31:0] $end
$var wire 32 # channel3 [31:0] $end
$var wire 32 $ channel2 [31:0] $end
$var wire 32 % channel1 [31:0] $end
$var wire 32 & channel0 [31:0] $end
$var reg 1 ' clock $end
$var reg 1 ( data $end
$var reg 1 ) fsync $end
$var reg 160 * mem [159:0] $end
$var reg 1 + reset $end
$var integer 32 , i [31:0] $end
$var integer 32 - j [31:0] $end
$scope module deserializer $end
$var wire 32 . ch0 [31:0] $end
$var wire 32 / ch1 [31:0] $end
$var wire 32 0 ch2 [31:0] $end
$var wire 32 1 ch3 [31:0] $end
$var wire 32 2 ch4 [31:0] $end
$var wire 1 ' clock $end
$var wire 1 + reset $end
$var wire 1 ' tdm_clk $end
$var wire 1 ( tdm_data $end
$var wire 1 ) tdm_sync $end
$var wire 1 ! word_ready $end
$var parameter 4 3 CH0_DEC $end
$var parameter 4 4 CH1_DEC $end
$var parameter 4 5 CH2_DEC $end
$var parameter 4 6 CH3_DEC $end
$var parameter 4 7 CH4_DEC $end
$var parameter 4 8 IDLE $end
$var parameter 32 9 SIZE_08T $end
$var parameter 32 : SIZE_32T $end
$var reg 32 ; ch0_data [31:0] $end
$var reg 32 < ch1_data [31:0] $end
$var reg 32 = ch2_data [31:0] $end
$var reg 32 > ch3_data [31:0] $end
$var reg 32 ? ch4_data [31:0] $end
$var reg 8 @ count [7:0] $end
$var reg 1 A ready $end
$upscope $end
$upscope $end
$enddefinitions $end
$comment Show the parameter values. $end
$dumpall
b100000 :
b1000 9
b1111 8
b100 7
b11 6
b10 5
b1 4
b0 3
$end
#0
$dumpvars
xA
bx @
bx ?
bx >
bx =
bx <
bx ;
bx 2
bx 1
bx 0
bx /
bx .
b110 -
b101 ,
0+
b101010101010101010101011111101001010101010101010101010111111011010101010101010101010101111111000101010101010101010101011111111001010101010101010101010111100000 *
0)
x(
0'
bx &
bx %
bx $
bx #
bx "
x!
$end
#100
1'
#200
0'
#300
1'
#400
0'
#500
0!
0A
b0 "
b0 2
b0 ?
b0 #
b0 1
b0 >
b0 $
b0 0
b0 =
b0 %
b0 /
b0 <
b0 &
b0 .
b0 ;
b11111111 @
1'
1+
#600
0'
#700
1'
#800
0'
#900
1'
#1000
0'
#1100
1'
#1200
0'
#1300
1'
#1400
0'
#1500
b0 @
1'
1)
0+
#1600
0'
b0 ,
0)
#1700
b1 @
b0x &
b0x .
b0x ;
1'
#1800
0'
b1 ,
0(
#1900
b10 @
b0x0 &
b0x0 .
b0x0 ;
1'
#2000
0'
b10 ,
#2100
b11 @
b0x00 &
b0x00 .
b0x00 ;
1'
#2200
0'
b11 ,
#2300
b100 @
b0x000 &
b0x000 .
b0x000 ;
1'
#2400
0'
b100 ,
#2500
b101 @
b0x0000 &
b0x0000 .
b0x0000 ;
1'
#2600
0'
b101 ,
#2700
b110 @
b0x00000 &
b0x00000 .
b0x00000 ;
1'
#2800
0'
b110 ,
1(
#2900
b111 @
b0x000001 &
b0x000001 .
b0x000001 ;
1'
#3000
0'
b111 ,
#3100
b1000 @
b0x0000011 &
b0x0000011 .
b0x0000011 ;
1'
#3200
0'
b1000 ,
#3300
b1001 @
b0x00000111 &
b0x00000111 .
b0x00000111 ;
1'
#3400
0'
b1001 ,
#3500
b1010 @
b0x000001111 &
b0x000001111 .
b0x000001111 ;
1'
#3600
0'
b1010 ,
0(
#3700
b1011 @
b0x0000011110 &
b0x0000011110 .
b0x0000011110 ;
1'
#3800
0'
b1011 ,
1(
#3900
b1100 @
b0x00000111101 &
b0x00000111101 .
b0x00000111101 ;
1'
#4000
0'
b1100 ,
0(
#4100
b1101 @
b0x000001111010 &
b0x000001111010 .
b0x000001111010 ;
1'
#4200
0'
b1101 ,
1(
#4300
b1110 @
b0x0000011110101 &
b0x0000011110101 .
b0x0000011110101 ;
1'
#4400
0'
b1110 ,
0(
#4500
b1111 @
b0x00000111101010 &
b0x00000111101010 .
b0x00000111101010 ;
1'
#4600
0'
b1111 ,
1(
#4700
b10000 @
b0x000001111010101 &
b0x000001111010101 .
b0x000001111010101 ;
1'
#4800
0'
b10000 ,
0(
#4900
b10001 @
1'
#5000
0'
b10001 ,
1(
#5100
b10010 @
b1 %
b1 /
b1 <
1'
#5200
0'
b10010 ,
0(
#5300
b10011 @
b10 %
b10 /
b10 <
1'
#5400
0'
b10011 ,
1(
#5500
b10100 @
b101 %
b101 /
b101 <
1'
#5600
0'
b10100 ,
0(
#5700
b10101 @
b1010 %
b1010 /
b1010 <
1'
#5800
0'
b10101 ,
1(
#5900
b10110 @
b10101 %
b10101 /
b10101 <
1'
#6000
0'
b10110 ,
0(
#6100
b10111 @
b101010 %
b101010 /
b101010 <
1'
#6200
0'
b10111 ,
1(
#6300
b11000 @
b1010101 %
b1010101 /
b1010101 <
1'
#6400
0'
b11000 ,
0(
#6500
b11001 @
b10101010 %
b10101010 /
b10101010 <
1'
#6600
0'
b11001 ,
1(
#6700
b11010 @
b101010101 %
b101010101 /
b101010101 <
1'
#6800
0'
b11010 ,
0(
#6900
b11011 @
b1010101010 %
b1010101010 /
b1010101010 <
1'
#7000
0'
b11011 ,
1(
#7100
b11100 @
b10101010101 %
b10101010101 /
b10101010101 <
1'
#7200
0'
b11100 ,
0(
#7300
b11101 @
b101010101010 %
b101010101010 /
b101010101010 <
1'
#7400
0'
b11101 ,
1(
#7500
b11110 @
b1010101010101 %
b1010101010101 /
b1010101010101 <
1'
#7600
0'
b11110 ,
0(
#7700
b11111 @
b10101010101010 %
b10101010101010 /
b10101010101010 <
1'
#7800
0'
b11111 ,
1(
#7900
b100000 @
b101010101010101 %
b101010101010101 /
b101010101010101 <
1'
#8000
0'
b100000 ,
0(
#8100
b100001 @
1'
#8200
0'
b100001 ,
#8300
b100010 @
1'
#8400
0'
b100010 ,
1(
#8500
b100011 @
b1 $
b1 0
b1 =
1'
#8600
0'
b100011 ,
#8700
b100100 @
b11 $
b11 0
b11 =
1'
#8800
0'
b100100 ,
#8900
b100101 @
b111 $
b111 0
b111 =
1'
#9000
0'
b100101 ,
#9100
b100110 @
b1111 $
b1111 0
b1111 =
1'
#9200
0'
b100110 ,
#9300
b100111 @
b11111 $
b11111 0
b11111 =
1'
#9400
0'
b100111 ,
#9500
b101000 @
b111111 $
b111111 0
b111111 =
1'
#9600
0'
b101000 ,
#9700
b101001 @
b1111111 $
b1111111 0
b1111111 =
1'
#9800
0'
b101001 ,
#9900
b101010 @
b11111111 $
b11111111 0
b11111111 =
1'
#10000
0'
b101010 ,
0(
#10100
b101011 @
b111111110 $
b111111110 0
b111111110 =
1'
#10200
0'
b101011 ,
1(
#10300
b101100 @
b1111111101 $
b1111111101 0
b1111111101 =
1'
#10400
0'
b101100 ,
0(
#10500
b101101 @
b11111111010 $
b11111111010 0
b11111111010 =
1'
#10600
0'
b101101 ,
1(
#10700
b101110 @
b111111110101 $
b111111110101 0
b111111110101 =
1'
#10800
0'
b101110 ,
0(
#10900
b101111 @
b1111111101010 $
b1111111101010 0
b1111111101010 =
1'
#11000
0'
b101111 ,
1(
#11100
b110000 @
b11111111010101 $
b11111111010101 0
b11111111010101 =
1'
#11200
0'
b110000 ,
0(
#11300
b110001 @
1'
#11400
0'
b110001 ,
1(
#11500
b110010 @
b1 #
b1 1
b1 >
1'
#11600
0'
b110010 ,
0(
#11700
b110011 @
b10 #
b10 1
b10 >
1'
#11800
0'
b110011 ,
1(
#11900
b110100 @
b101 #
b101 1
b101 >
1'
#12000
0'
b110100 ,
0(
#12100
b110101 @
b1010 #
b1010 1
b1010 >
1'
#12200
0'
b110101 ,
1(
#12300
b110110 @
b10101 #
b10101 1
b10101 >
1'
#12400
0'
b110110 ,
0(
#12500
b110111 @
b101010 #
b101010 1
b101010 >
1'
#12600
0'
b110111 ,
1(
#12700
b111000 @
b1010101 #
b1010101 1
b1010101 >
1'
#12800
0'
b111000 ,
0(
#12900
b111001 @
b10101010 #
b10101010 1
b10101010 >
1'
#13000
0'
b111001 ,
1(
#13100
b111010 @
b101010101 #
b101010101 1
b101010101 >
1'
#13200
0'
b111010 ,
0(
#13300
b111011 @
b1010101010 #
b1010101010 1
b1010101010 >
1'
#13400
0'
b111011 ,
1(
#13500
b111100 @
b10101010101 #
b10101010101 1
b10101010101 >
1'
#13600
0'
b111100 ,
0(
#13700
b111101 @
b101010101010 #
b101010101010 1
b101010101010 >
1'
#13800
0'
b111101 ,
1(
#13900
b111110 @
b1010101010101 #
b1010101010101 1
b1010101010101 >
1'
#14000
0'
b111110 ,
0(
#14100
b111111 @
b10101010101010 #
b10101010101010 1
b10101010101010 >
1'
#14200
0'
b111111 ,
1(
#14300
b1000000 @
b101010101010101 #
b101010101010101 1
b101010101010101 >
1'
#14400
0'
b1000000 ,
0(
#14500
b1000001 @
1'
#14600
0'
b1000001 ,
#14700
b1000010 @
1'
#14800
0'
b1000010 ,
#14900
b1000011 @
1'
#15000
0'
b1000011 ,
1(
#15100
b1000100 @
b1 "
b1 2
b1 ?
1'
#15200
0'
b1000100 ,
#15300
b1000101 @
b11 "
b11 2
b11 ?
1'
#15400
0'
b1000101 ,
#15500
b1000110 @
b111 "
b111 2
b111 ?
1'
#15600
0'
b1000110 ,
#15700
b1000111 @
b1111 "
b1111 2
b1111 ?
1'
#15800
0'
b1000111 ,
#15900
b1001000 @
b11111 "
b11111 2
b11111 ?
1'
#16000
0'
b1001000 ,
#16100
b1001001 @
b111111 "
b111111 2
b111111 ?
1'
#16200
0'
b1001001 ,
#16300
b1001010 @
b1111111 "
b1111111 2
b1111111 ?
1'
#16400
0'
b1001010 ,
0(
#16500
b1001011 @
b11111110 "
b11111110 2
b11111110 ?
1'
#16600
0'
b1001011 ,
1(
#16700
b1001100 @
b111111101 "
b111111101 2
b111111101 ?
1'
#16800
0'
b1001100 ,
0(
#16900
b1001101 @
b1111111010 "
b1111111010 2
b1111111010 ?
1'
#17000
0'
b1001101 ,
1(
#17100
b1001110 @
b11111110101 "
b11111110101 2
b11111110101 ?
1'
#17200
0'
b1001110 ,
0(
#17300
b1001111 @
b111111101010 "
b111111101010 2
b111111101010 ?
1'
#17400
0'
b1001111 ,
1(
#17500
1!
1A
b11111111 @
b1111111010101 "
b1111111010101 2
b1111111010101 ?
1'
#17600
0'
b1010000 ,
0(
#17700
0!
0A
1'
#17800
0'
b1010001 ,
1(
#17900
1'
#18000
0'
b1010010 ,
0(
#18100
1'
#18200
0'
b1010011 ,
1(
#18300
1'
#18400
0'
b1010100 ,
0(
#18500
1'
#18600
0'
b1010101 ,
1(
#18700
1'
#18800
0'
b1010110 ,
0(
#18900
1'
#19000
0'
b1010111 ,
1(
#19100
1'
#19200
0'
b1011000 ,
0(
#19300
1'
#19400
0'
b1011001 ,
1(
#19500
1'
#19600
0'
b1011010 ,
0(
#19700
1'
#19800
0'
b1011011 ,
1(
#19900
1'
#20000
0'
b1011100 ,
0(
#20100
1'
#20200
0'
b1011101 ,
1(
#20300
1'
#20400
0'
b1011110 ,
0(
#20500
1'
#20600
0'
b1011111 ,
1(
#20700
1'
#20800
0'
b1100000 ,
0(
#20900
1'
#21000
0'
b1100001 ,
1(
#21100
1'
#21200
0'
b1100010 ,
#21300
1'
#21400
0'
b1100011 ,
0(
#21500
1'
#21600
0'
b1100100 ,
1(
#21700
1'
#21800
0'
b1100101 ,
#21900
1'
#22000
0'
b1100110 ,
#22100
1'
#22200
0'
b1100111 ,
#22300
1'
#22400
0'
b1101000 ,
#22500
1'
#22600
0'
b1101001 ,
#22700
1'
#22800
0'
b1101010 ,
0(
#22900
1'
#23000
0'
b1101011 ,
1(
#23100
1'
#23200
0'
b1101100 ,
0(
#23300
1'
#23400
0'
b1101101 ,
1(
#23500
1'
#23600
0'
b1101110 ,
0(
#23700
1'
#23800
0'
b1101111 ,
1(
#23900
1'
#24000
0'
b1110000 ,
0(
#24100
1'
#24200
0'
b1110001 ,
1(
#24300
1'
#24400
0'
b1110010 ,
0(
#24500
1'
#24600
0'
b1110011 ,
1(
#24700
1'
#24800
0'
b1110100 ,
0(
#24900
1'
#25000
0'
b1110101 ,
1(
#25100
1'
#25200
0'
b1110110 ,
0(
#25300
1'
#25400
0'
b1110111 ,
1(
#25500
1'
#25600
0'
b1111000 ,
0(
#25700
1'
#25800
0'
b1111001 ,
1(
#25900
1'
#26000
0'
b1111010 ,
0(
#26100
1'
#26200
0'
b1111011 ,
1(
#26300
1'
#26400
0'
b1111100 ,
0(
#26500
1'
#26600
0'
b1111101 ,
1(
#26700
1'
#26800
0'
b1111110 ,
0(
#26900
1'
#27000
0'
b1111111 ,
1(
#27100
1'
#27200
0'
b10000000 ,
0(
#27300
1'
#27400
0'
b10000001 ,
#27500
1'
#27600
0'
b10000010 ,
1(
#27700
1'
#27800
0'
b10000011 ,
0(
#27900
1'
#28000
0'
b10000100 ,
1(
#28100
1'
#28200
0'
b10000101 ,
#28300
1'
#28400
0'
b10000110 ,
#28500
1'
#28600
0'
b10000111 ,
#28700
1'
#28800
0'
b10001000 ,
#28900
1'
#29000
0'
b10001001 ,
#29100
1'
#29200
0'
b10001010 ,
0(
#29300
1'
#29400
0'
b10001011 ,
1(
#29500
1'
#29600
0'
b10001100 ,
0(
#29700
1'
#29800
0'
b10001101 ,
1(
#29900
1'
#30000
0'
b10001110 ,
0(
#30100
1'
#30200
0'
b10001111 ,
1(
#30300
1'
#30400
0'
b10010000 ,
0(
#30500
1'
#30600
0'
b10010001 ,
1(
#30700
1'
#30800
0'
b10010010 ,
0(
#30900
1'
#31000
0'
b10010011 ,
1(
#31100
1'
#31200
0'
b10010100 ,
0(
#31300
1'
#31400
0'
b10010101 ,
1(
#31500
1'
#31600
0'
b10010110 ,
0(
#31700
1'
#31800
0'
b10010111 ,
1(
#31900
1'
#32000
0'
b10011000 ,
0(
#32100
1'
#32200
0'
b10011001 ,
1(
#32300
1'
#32400
0'
b10011010 ,
0(
#32500
1'
#32600
0'
b10011011 ,
1(
#32700
1'
#32800
0'
b10011100 ,
0(
#32900
1'
#33000
0'
b10011101 ,
1(
#33100
1'
#33200
0'
b10011110 ,
0(
#33300
1'
#33400
0'
b10011111 ,
1(
#33500
1'
#33600
0'
b10100000 ,
0(
